disanda.py
setup.py
disanda.egg-info/PKG-INFO
disanda.egg-info/SOURCES.txt
disanda.egg-info/dependency_links.txt
disanda.egg-info/top_level.txt