Metadata-Version: 1.0
Name: disanda
Version: 0.2
Summary: 2th issue
Home-page: http://disanda.github.io
Author: disanda
Author-email: disanda@foxmail.com
License: UNKNOWN
Platform: UNKNOWN
